src/digital/i2c_slave_config.v
module i2c_slave_config #(
    parameter SLAVE_ADDR = 7'h50
)(
    input  wire       clk,           
    input  wire       en,
    input  wire       scl,
    input  wire       sda_in,
    output reg        sda_out,       
    output reg        sda_oe,        
    output wire [7:0] threshold_reg,
    output wire [7:0] timeout_reg,
    output wire [7:0] capacitor_ctrl_reg
);

    // Block 1: edge detection for SCL and SDA
    reg scl_d1, scl_d2, sda_d1, sda_d2;
    always @(posedge clk or posedge en) begin
        if (en) begin
            scl_d1 <= 1'b1; scl_d2 <= 1'b1;
            sda_d1 <= 1'b1; sda_d2 <= 1'b1;
        end else begin
            scl_d1 <= scl;     scl_d2 <= scl_d1;
            sda_d1 <= sda_in;  sda_d2 <= sda_d1;
        end
    end

    wire scl_rise  = scl_d1 & ~scl_d2;
    wire scl_fall  = ~scl_d1 & scl_d2;
    wire start_det = scl_d1 & scl_d2 & ~sda_d1 & sda_d2;
    wire stop_det  = scl_d1 & scl_d2 & sda_d1 & ~sda_d2;

    // Block 2: FSM States 
    localparam IDLE = 3'd0, ADDR = 3'd1, ADDR_ACK = 3'd2, REGADDR = 3'd3, REGADDR_ACK = 3'd4, DATA = 3'd5, DATA_ACK = 3'd6;

    reg [2:0] state;
    reg [3:0] bit_cnt;
    reg       write_en;

    wire shift_en = (state == ADDR || state == REGADDR || state == DATA) && scl_rise;

    always @(posedge clk or posedge en) begin
        if (en) begin
            state <= IDLE; 
            bit_cnt <= 4'd0; 
            sda_out <= 1'b1; 
            sda_oe <= 1'b0; 
            write_en <= 1'b0;
        end else begin
            write_en <= 1'b0; // Default: clear flag write_en

            if (start_det) begin 
                state <= ADDR; 
                bit_cnt <= 4'd0; 
                sda_oe <= 1'b0; 
            end 
            else if (stop_det) begin 
                state <= IDLE; 
                sda_oe <= 1'b0; 
            end 
            else begin
                case (state)
                    ADDR: begin
                        if (shift_en) begin
                            bit_cnt <= bit_cnt + 1'b1;
                            if (bit_cnt == 4'd7) state <= ADDR_ACK;
                        end
                    end
                    
                    ADDR_ACK: begin
                        if (scl_fall) begin
                            if (sda_oe == 1'b0) begin
                                // scl fall 9 check: if address matches and R/W bit is 0 (write), then ACK
                                if (parallel_data[7:1] == SLAVE_ADDR && parallel_data[0] == 1'b0) begin
                                    sda_out <= 1'b0; 
                                    sda_oe <= 1'b1; 
                                end else begin
                                    state <= IDLE; // NACK, wrong address or R/W bit is 1 (read), go back to IDLE
                                end
                            end else begin
                                // scl fall 10: release SDA and move to REGADDR state
                                sda_oe <= 1'b0;
                                state <= REGADDR;
                                bit_cnt <= 4'd0;
                            end
                        end
                    end

                    REGADDR: begin
                        if (shift_en) begin
                            bit_cnt <= bit_cnt + 1'b1;
                            if (bit_cnt == 4'd7) state <= REGADDR_ACK;
                        end
                    end
                    
                    REGADDR_ACK: begin
                        if (scl_fall) begin
                            if (sda_oe == 1'b0) begin
                                sda_out <= 1'b0; 
                                sda_oe <= 1'b1; 
                            end else begin
                                sda_oe <= 1'b0; 
                                state <= DATA;
                                bit_cnt <= 4'd0;
                            end
                        end
                    end

                    DATA: begin
                        if (shift_en) begin
                            bit_cnt <= bit_cnt + 1'b1;
                            if (bit_cnt == 4'd7) state <= DATA_ACK;
                        end
                    end

                    DATA_ACK: begin
                        if (scl_fall) begin
                            if (sda_oe == 1'b0) begin
                                sda_out <= 1'b0; 
                                sda_oe <= 1'b1; 
                                write_en <= 1'b1; // Trigger write_en to indicate that a full byte has been received and should be written to the appropriate register
                            end else begin
                                sda_oe <= 1'b0; 
                                state <= DATA; // Loop back to DATA state for next byte
                                bit_cnt <= 4'd0;
                            end
                        end
                    end
                    
                    default: state <= IDLE;
                endcase
            end
        end
    end

    // Block 3: Shift Register 
    reg [7:0] shift_reg_internal;
    reg [1:0] reg_addr;
    wire [7:0] parallel_data = shift_reg_internal;

    always @(posedge clk or posedge en) begin
        if (en) begin
            shift_reg_internal <= 8'h00;
            reg_addr           <= 2'b00;
        end else begin
            if (shift_en) begin
                shift_reg_internal <= {shift_reg_internal[6:0], sda_d1};
            end
            
            // Simpan alamat register tepat di SCL fall ke-8 saat REGADDR_ACK
            if (state == REGADDR_ACK && scl_fall && sda_oe == 1'b0) begin
                reg_addr <= shift_reg_internal[1:0];
            end
        end
    end

    // Block 4: Decoder & Registers
    // Register Map:
    // 0x00: threshold_reg (default: 0x05)
    // 0x01: timeout_reg (default: 0xA0)
    // 0x02: capacitor_ctrl_reg (default: 0x00)
    // 0x03: reserved for future use
    
    reg [7:0] threshold_int, timeout_int, capacitor_ctrl_int;
    assign threshold_reg      = threshold_int;
    assign timeout_reg        = timeout_int;
    assign capacitor_ctrl_reg = capacitor_ctrl_int;

    always @(posedge clk or posedge en) begin
        if (en) begin
            threshold_int       <= 8'h05; 
            timeout_int         <= 8'hA0;
            capacitor_ctrl_int  <= 8'h00;
        end else if (write_en) begin
            case (reg_addr)
                2'b00: threshold_int       <= parallel_data;
                2'b01: timeout_int         <= parallel_data;
                2'b10: capacitor_ctrl_int  <= parallel_data;
                default: ; // Reserved register, do nothing
            endcase
        end
    end
endmodule

src/digital/tb/tb_i2c_slave_config.v
`timescale 1ns / 1ps

module tb_i2c_slave_config;

    // Parameter
    parameter CLK_PERIOD = 10; // 100MHz system clock

    // Inputs
    reg clk;
    reg en;
    reg scl;
    reg sda_in;

    // Outputs
    wire sda_out;
    wire sda_oe;
    wire [7:0] threshold_reg;
    wire [7:0] timeout_reg;
    wire [7:0] capacitor_ctrl_reg;

    // DUT Instantiation
    i2c_slave_config #(.SLAVE_ADDR(7'h50)) u_i2c (
        .clk(clk),
        .en(en),
        .scl(scl),
        .sda_in(sda_in),
        .sda_out(sda_out),
        .sda_oe(sda_oe),
        .threshold_reg(threshold_reg),
        .timeout_reg(timeout_reg),
        .capacitor_ctrl_reg(capacitor_ctrl_reg)
    );

    // Clock Generation
    always #(CLK_PERIOD/2) clk = ~clk;

    // task for sending a byte over I2C
    task i2c_write_byte;
        input [7:0] data;
        integer i;
        begin
            // Fase Data (8 Bit)
            for (i = 7; i >= 0; i = i - 1) begin
                scl = 0; #50;
                sda_in = data[i]; #50;
                scl = 1; #100; // SCL High pulse
                scl = 0; #50;
            end
            
            //  Fase ACK/NACK
            sda_in = 1; // master releases SDA for ACK/NACK
            scl = 1; #50; // SCL High
            
            // evaluation response from Slave in mid SCL High
            if (sda_oe == 1'b1 && sda_out == 1'b0) begin
                $display("[%0t ns] ACK Received for byte: 0x%h", $time, data);
            end else begin
                $display("[%0t ns] ERROR: NACK! Slave did not respond to byte: 0x%h", $time, data);
            end
            
            #50; scl = 0; #50; // Complete SCL Low
        end
    endtask

    initial begin
        $dumpfile("tb/vcd_file/i2c_sim.vcd");
        $dumpvars(0, tb_i2c_slave_config);

        // Init
        clk = 0; en = 1; scl = 1; sda_in = 1;
        #100 en = 0; #100;

        $display("=== START SIMULATION I2C WRITE ===");

        // 1. START CONDITION
        sda_in = 0; #50; scl = 0; 

        // 2. send Address (0x50 << 1 | WriteBit 0 = 0xA0)
        i2c_write_byte(8'hA0); 

        // 3. send Register Address (0x00 untuk Threshold)
        i2c_write_byte(8'h00);

        // 4. send Data Threshold (Misal: 0x0A)
        i2c_write_byte(8'h0A);

        // 5. STOP CONDITION
        scl = 0; sda_in = 0; #50;
        scl = 1; #50;
        sda_in = 1; #100;

        #200;
        // check if the threshold register has been updated correctly
        if (threshold_reg == 8'h0A) 
            $display("SUCCESS: Threshold successfully updated to 0x0A");
        else 
            $display("FAILED: Threshold not updated correctly. Expected 0x0A, got %h", threshold_reg);

        $display("\n=== START SIMULATION I2C WRITE (TIMEOUT REG) ===");

        // 1. START CONDITION
        sda_in = 0; #50; scl = 0; 

        // 2. send Address (0x50 << 1 | WriteBit 0 = 0xA0)
        i2c_write_byte(8'hA0); 

        // 3. send Register Address (0x01 untuk Timeout)
        i2c_write_byte(8'h01);

        // 4. send Data Timeout (Misal: 0xFF)
        i2c_write_byte(8'hFF);

        // 5. STOP CONDITION
        scl = 0; sda_in = 0; #50;
        scl = 1; #50;
        sda_in = 1; #100;

        #200;
        // Cek hasil akhir di register timeout
        if (timeout_reg == 8'hFF) 
            $display("SUCCESS: timeout register successfully updated to 0xFF");
        else 
            $display("FAILED: Timeout salah. Diharapkan 0xFF, terbaca %h", timeout_reg);

        $display("\n=== START SIMULATION I2C WRITE (CAPACITOR CTRL REG) ===");

        // 1. START CONDITION
        sda_in = 0; #50; scl = 0; 

        // 2. send Address (0x50 << 1 | WriteBit 0 = 0xA0)
        i2c_write_byte(8'hA0); 

        // 3. send Register Address (0x02 untuk Capacitor Control)
        i2c_write_byte(8'h02);

        // 4. send Data Capacitor Control (Misal: 0x55)
        i2c_write_byte(8'h55);

        // 5. STOP CONDITION
        scl = 0; sda_in = 0; #50;
        scl = 1; #50;
        sda_in = 1; #100;

        #200;
        // Cek hasil akhir di register capacitor control
        if (capacitor_ctrl_reg == 8'h55) 
            $display("SUCCESS: Capacitor Control register successfully updated to 0x55");
        else 
            $display("FAILED: Capacitor Control salah. Diharapkan 0x55, terbaca %h", capacitor_ctrl_reg);

        $display("\n=== TEST MULTIPLE CAPACITOR VALUES ===");
        
        // Test with different capacitor control value (0xAA)
        sda_in = 0; #50; scl = 0; 
        i2c_write_byte(8'hA0); 
        i2c_write_byte(8'h02);
        i2c_write_byte(8'hAA);
        scl = 0; sda_in = 0; #50;
        scl = 1; #50;
        sda_in = 1; #100;

        #200;
        if (capacitor_ctrl_reg == 8'hAA) 
            $display("SUCCESS: Capacitor Control register successfully updated to 0xAA");
        else 
            $display("FAILED: Capacitor Control salah. Diharapkan 0xAA, terbaca %h", capacitor_ctrl_reg);

        $display("\n=== VERIFY ALL REGISTERS ===");
        $display("Threshold Register    : 0x%h (Expected: 0x0A)", threshold_reg);
        $display("Timeout Register      : 0x%h (Expected: 0xFF)", timeout_reg);
        $display("Capacitor Ctrl Register: 0x%h (Expected: 0xAA)", capacitor_ctrl_reg);
        
        $display("\n=== simulation complete ===");
        $finish;
    end
endmodule

src/digital/tb/vcd_file/i2c_sim.vcd
$date
	Mon Aug 24 08:53:24 2026
$end
$version
	Icarus Verilog
$end
$timescale
	1ps
$end
$scope module tb_i2c_slave_config $end
$var wire 8 ! timeout_reg [7:0] $end
$var wire 8 " threshold_reg [7:0] $end
$var wire 1 # sda_out $end
$var wire 1 $ sda_oe $end
$var wire 8 % capacitor_ctrl_reg [7:0] $end
$var reg 1 & clk $end
$var reg 1 ' en $end
$var reg 1 ( scl $end
$var reg 1 ) sda_in $end
$scope module u_i2c $end
$var wire 8 * capacitor_ctrl_reg [7:0] $end
$var wire 1 & clk $end
$var wire 1 ' en $end
$var wire 8 + parallel_data [7:0] $end
$var wire 1 ( scl $end
$var wire 1 , scl_fall $end
$var wire 1 - scl_rise $end
$var wire 1 ) sda_in $end
$var wire 1 . shift_en $end
$var wire 1 / start_det $end
$var wire 1 0 stop_det $end
$var wire 8 1 threshold_reg [7:0] $end
$var wire 8 2 timeout_reg [7:0] $end
$var reg 4 3 bit_cnt [3:0] $end
$var reg 8 4 capacitor_ctrl_int [7:0] $end
$var reg 2 5 reg_addr [1:0] $end
$var reg 1 6 scl_d1 $end
$var reg 1 7 scl_d2 $end
$var reg 1 8 sda_d1 $end
$var reg 1 9 sda_d2 $end
$var reg 1 $ sda_oe $end
$var reg 1 # sda_out $end
$var reg 8 : shift_reg_internal [7:0] $end
$var reg 3 ; state [2:0] $end
$var reg 8 < threshold_int [7:0] $end
$var reg 8 = timeout_int [7:0] $end
$var reg 1 > write_en $end
$upscope $end
$scope task i2c_write_byte $end
$var reg 8 ? data [7:0] $end
$var integer 32 @ i [31:0] $end
$upscope $end
$upscope $end
$enddefinitions $end
#0
$dumpvars
bx @
bx ?
0>
b10100000 =
b101 <
b0 ;
b0 :
19
18
17
16
b0 5
b0 4
b0 3
b10100000 2
b101 1
00
0/
0.
0-
0,
b0 +
b0 *
1)
1(
1'
0&
b0 %
0$
1#
b101 "
b10100000 !
$end
#5000
1&
#10000
0&
#15000
1&
#20000
0&
#25000
1&
#30000
0&
#35000
1&
#40000
0&
#45000
1&
#50000
0&
#55000
1&
#60000
0&
#65000
1&
#70000
0&
#75000
1&
#80000
0&
#85000
1&
#90000
0&
#95000
1&
#100000
0&
0'
#105000
1&
#110000
0&
#115000
1&
#120000
0&
#125000
1&
#130000
0&
#135000
1&
#140000
0&
#145000
1&
#150000
0&
#155000
1&
#160000
0&
#165000
1&
#170000
0&
#175000
1&
#180000
0&
#185000
1&
#190000
0&
#195000
1&
#200000
0&
0)
#205000
1/
08
1&
#210000
0&
#215000
0/
09
b1 ;
1&
#220000
0&
#225000
1&
#230000
0&
#235000
1&
#240000
0&
#245000
1&
#250000
0&
b111 @
b10100000 ?
0(
#255000
1,
06
1&
#260000
0&
#265000
0,
07
1&
#270000
0&
#275000
1&
#280000
0&
#285000
1&
#290000
0&
#295000
1&
#300000
0&
1)
#305000
18
1&
#310000
0&
#315000
19
1&
#320000
0&
#325000
1&
#330000
0&
#335000
1&
#340000
0&
#345000
1&
#350000
0&
1(
#355000
1.
1-
16
1&
#360000
0&
#365000
0.
0-
b1 +
b1 :
b1 3
17
1&
#370000
0&
#375000
1&
#380000
0&
#385000
1&
#390000
0&
#395000
1&
#400000
0&
#405000
1&
#410000
0&
#415000
1&
#420000
0&
#425000
1&
#430000
0&
#435000
1&
#440000
0&
#445000
1&
#450000
0&
0(
#455000
1,
06
1&
#460000
0&
#465000
0,
07
1&
#470000
0&
#475000
1&
#480000
0&
#485000
1&
#490000
0&
#495000
1&
#500000
0&
b110 @
#505000
1&
#510000
0&
#515000
1&
#520000
0&
#525000
1&
#530000
0&
#535000
1&
#540000
0&
#545000
1&
#550000
0&
0)
#555000
08
1&
#560000
0&
#565000
09
1&
#570000
0&
#575000
1&
#580000
0&
#585000
1&
#590000
0&
#595000
1&
#600000
0&
1(
#605000
1.
1-
16
1&
#610000
0&
#615000
0.
0-
17
b10 3
b10 +
b10 :
1&
#620000
0&
#625000
1&
#630000
0&
#635000
1&
#640000
0&
#645000
1&
#650000
0&
#655000
1&
#660000
0&
#665000
1&
#670000
0&
#675000
1&
#680000
0&
#685000
1&
#690000
0&
#695000
1&
#700000
0&
0(
#705000
1,
06
1&
#710000
0&
#715000
0,
07
1&
#720000
0&
#725000
1&
#730000
0&
#735000
1&
#740000
0&
#745000
1&
#750000
0&
b101 @
#755000
1&
#760000
0&
#765000
1&
#770000
0&
#775000
1&
#780000
0&
#785000
1&
#790000
0&
#795000
1&
#800000
0&
1)
#805000
18
1&
#810000
0&
#815000
19
1&
#820000
0&
#825000
1&
#830000
0&
#835000
1&
#840000
0&
#845000
1&
#850000
0&
1(
#855000
1.
1-
16
1&
#860000
0&
#865000
0.
0-
b101 +
b101 :
b11 3
17
1&
#870000
0&
#875000
1&
#880000
0&
#885000
1&
#890000
0&
#895000
1&
#900000
0&
#905000
1&
#910000
0&
#915000
1&
#920000
0&
#925000
1&
#930000
0&
#935000
1&
#940000
0&
#945000
1&
#950000
0&
0(
#955000
1,
06
1&
#960000
0&
#965000
0,
07
1&
#970000
0&
#975000
1&
#980000
0&
#985000
1&
#990000
0&
#995000
1&
#1000000
0&
b100 @
#1005000
1&
#1010000
0&
#1015000
1&
#1020000
0&
#1025000
1&
#1030000
0&
#1035000
1&
#1040000
0&
#1045000
1&
#1050000
0&
0)
#1055000
08
1&
#1060000
0&
#1065000
09
1&
#1070000
0&
#1075000
1&
#1080000
0&
#1085000
1&
#1090000
0&
#1095000
1&
#1100000
0&
1(
#1105000
1.
1-
16
1&
#1110000
0&
#1115000
0.
0-
17
b100 3
b1010 +
b1010 :
1&
#1120000
0&
#1125000
1&
#1130000
0&
#1135000
1&
#1140000
0&
#1145000
1&
#1150000
0&
#1155000
1&
#1160000
0&
#1165000
1&
#1170000
0&
#1175000
1&
#1180000
0&
#1185000
1&
#1190000
0&
#1195000
1&
#1200000
0&
0(
#1205000
1,
06
1&
#1210000
0&
#1215000
0,
07
1&
#1220000
0&
#1225000
1&
#1230000
0&
#1235000
1&
#1240000
0&
#1245000
1&
#1250000
0&
b11 @
#1255000
1&
#1260000
0&
#1265000
1&
#1270000
0&
#1275000
1&
#1280000
0&
#1285000
1&
#1290000
0&
#1295000
1&
#1300000
0&
#1305000
1&
#1310000
0&
#1315000
1&
#1320000
0&
#1325000
1&
#1330000
0&
#1335000
1&
#1340000
0&
#1345000
1&
#1350000
0&
1(
#1355000
1.
1-
16
1&
#1360000
0&
#1365000
0.
0-
b10100 +
b10100 :
b101 3
17
1&
#1370000
0&
#1375000
1&
#1380000
0&
#1385000
1&
#1390000
0&
#1395000
1&
#1400000
0&
#1405000
1&
#1410000
0&
#1415000
1&
#1420000
0&
#1425000
1&
#1430000
0&
#1435000
1&
#1440000
0&
#1445000
1&
#1450000
0&
0(
#1455000
1,
06
1&
#1460000
0&
#1465000
0,
07
1&
#1470000
0&
#1475000
1&
#1480000
0&
#1485000
1&
#1490000
0&
#1495000
1&
#1500000
0&
b10 @
#1505000
1&
#1510000
0&
#1515000
1&
#1520000
0&
#1525000
1&
#1530000
0&
#1535000
1&
#1540000
0&
#1545000
1&
#1550000
0&
#1555000
1&
#1560000
0&
#1565000
1&
#1570000
0&
#1575000
1&
#1580000
0&
#1585000
1&
#1590000
0&
#1595000
1&
#1600000
0&
1(
#1605000
1.
1-
16
1&
#1610000
0&
#1615000
0.
0-
17
b110 3
b101000 +
b101000 :
1&
#1620000
0&
#1625000
1&
#1630000
0&
#1635000
1&
#1640000
0&
#1645000
1&
#1650000
0&
#1655000
1&
#1660000
0&
#1665000
1&
#1670000
0&
#1675000
1&
#1680000
0&
#1685000
1&
#1690000
0&
#1695000
1&
#1700000
0&
0(
#1705000
1,
06
1&
#1710000
0&
#1715000
0,
07
1&
#1720000
0&
#1725000
1&
#1730000
0&
#1735000
1&
#1740000
0&
#1745000
1&
#1750000
0&
b1 @
#1755000
1&
#1760000
0&
#1765000
1&
#1770000
0&
#1775000
1&
#1780000
0&
#1785000
1&
#1790000
0&
#1795000
1&
#1800000
0&
#1805000
1&
#1810000
0&
#1815000
1&
#1820000
0&
#1825000
1&
#1830000
0&
#1835000
1&
#1840000
0&
#1845000
1&
#1850000
0&
1(
#1855000
1.
1-
16
1&
#1860000
0&
#1865000
0.
0-
b1010000 +
b1010000 :
b111 3
17
1&
#1870000
0&
#1875000
1&
#1880000
0&
#1885000
1&
#1890000
0&
#1895000
1&
#1900000
0&
#1905000
1&
#1910000
0&
#1915000
1&
#1920000
0&
#1925000
1&
#1930000
0&
#1935000
1&
#1940000
0&
#1945000
1&
#1950000
0&
0(
#1955000
1,
06
1&
#1960000
0&
#1965000
0,
07
1&
#1970000
0&
#1975000
1&
#1980000
0&
#1985000
1&
#1990000
0&
#1995000
1&
#2000000
0&
b0 @
#2005000
1&
#2010000
0&
#2015000
1&
#2020000
0&
#2025000
1&
#2030000
0&
#2035000
1&
#2040000
0&
#2045000
1&
#2050000
0&
#2055000
1&
#2060000
0&
#2065000
1&
#2070000
0&
#2075000
1&
#2080000
0&
#2085000
1&
#2090000
0&
#2095000
1&
#2100000
0&
1(
#2105000
1.
1-
16
1&
#2110000
0&
#2115000
0.
0-
17
b10 ;
b1000 3
b10100000 +
b10100000 :
1&
#2120000
0&
#2125000
1&
#2130000
0&
#2135000
1&
#2140000
0&
#2145000
1&
#2150000
0&
#2155000
1&
#2160000
0&
#2165000
1&
#2170000
0&
#2175000
1&
#2180000
0&
#2185000
1&
#2190000
0&
#2195000
1&
#2200000
0&
0(
#2205000
1,
06
1&
#2210000
0&
#2215000
0,
07
1$
0#
1&
#2220000
0&
#2225000
1&
#2230000
0&
#2235000
1&
#2240000
0&
#2245000
1&
#2250000
0&
1(
1)
b11111111111111111111111111111111 @
#2255000
1-
18
16
1&
#2260000
0&
#2265000
0-
19
17
1&
#2270000
0&
#2275000
1&
#2280000
0&
#2285000
1&
#2290000
0&
#2295000
1&
#2300000
0&
#2305000
1&
#2310000
0&
#2315000
1&
#2320000
0&
#2325000
1&
#2330000
0&
#2335000
1&
#2340000
0&
#2345000
1&
#2350000
0&
0(
#2355000
1,
06
1&
#2360000
0&
#2365000
0,
b0 3
b11 ;
0$
07
1&
#2370000
0&
#2375000
1&
#2380000
0&
#2385000
1&
#2390000
0&
#2395000
1&
#2400000
0&
b111 @
b0 ?
#2405000
1&
#2410000
0&
#2415000
1&
#2420000
0&
#2425000
1&
#2430000
0&
#2435000
1&
#2440000
0&
#2445000
1&
#2450000
0&
0)
#2455000
08
1&
#2460000
0&
#2465000
09
1&
#2470000
0&
#2475000
1&
#2480000
0&
#2485000
1&
#2490000
0&
#2495000
1&
#2500000
0&
1(
#2505000
1.
1-
16
1&
#2510000
0&
#2515000
0.
0-
17
b1 3
b1000000 +
b1000000 :
1&
#2520000
0&
#2525000
1&
#2530000
0&
#2535000
1&
#2540000
0&
#2545000
1&
#2550000
0&
#2555000
1&
#2560000
0&
#2565000
1&
#2570000
0&
#2575000
1&
#2580000
0&
#2585000
1&
#2590000
0&
#2595000
1&
#2600000
0&
0(
#2605000
1,
06
1&
#2610000
0&
#2615000
0,
07
1&
#2620000
0&
#2625000
1&
#2630000
0&
#2635000
1&
#2640000
0&
#2645000
1&
#2650000
0&
b110 @
#2655000
1&
#2660000
0&
#2665000
1&
#2670000
0&
#2675000
1&
#2680000
0&
#2685000
1&
#2690000
0&
#2695000
1&
#2700000
0&
#2705000
1&
#2710000
0&
#2715000
1&
#2720000
0&
#2725000
1&
#2730000
0&
#2735000
1&
#2740000
0&
#2745000
1&
#2750000
0&
1(
#2755000
1.
1-
16
1&
#2760000
0&
#2765000
0.
0-
b10000000 +
b10000000 :
b10 3
17
1&
#2770000
0&
#2775000
1&
#2780000
0&
#2785000
1&
#2790000
0&
#2795000
1&
#2800000
0&
#2805000
1&
#2810000
0&
#2815000
1&
#2820000
0&
#2825000
1&
#2830000
0&
#2835000
1&
#2840000
0&
#2845000
1&
#2850000
0&
0(
#2855000
1,
06
1&
#2860000
0&
#2865000
0,
07
1&
#2870000
0&
#2875000
1&
#2880000
0&
#2885000
1&
#2890000
0&
#2895000
1&
#2900000
0&
b101 @
#2905000
1&
#2910000
0&
#2915000
1&
#2920000
0&
#2925000
1&
#2930000
0&
#2935000
1&
#2940000
0&
#2945000
1&
#2950000
0&
#2955000
1&
#2960000
0&
#2965000
1&
#2970000
0&
#2975000
1&
#2980000
0&
#2985000
1&
#2990000
0&
#2995000
1&
#3000000
0&
1(
#3005000
1.
1-
16
1&
#3010000
0&
#3015000
0.
0-
17
b11 3
b0 +
b0 :
1&
#3020000
0&
#3025000
1&
#3030000
0&
#3035000
1&
#3040000
0&
#3045000
1&
#3050000
0&
#3055000
1&
#3060000
0&
#3065000
1&
#3070000
0&
#3075000
1&
#3080000
0&
#3085000
1&
#3090000
0&
#3095000
1&
#3100000
0&
0(
#3105000
1,
06
1&
#3110000
0&
#3115000
0,
07
1&
#3120000
0&
#3125000
1&
#3130000
0&
#3135000
1&
#3140000
0&
#3145000
1&
#3150000
0&
b100 @
#3155000
1&
#3160000
0&
#3165000
1&
#3170000
0&
#3175000
1&
#3180000
0&
#3185000
1&
#3190000
0&
#3195000
1&
#3200000
0&
#3205000
1&
#3210000
0&
#3215000
1&
#3220000
0&
#3225000
1&
#3230000
0&
#3235000
1&
#3240000
0&
#3245000
1&
#3250000
0&
1(
#3255000
1.
1-
16
1&
#3260000
0&
#3265000
0.
0-
b100 3
17
1&
#3270000
0&
#3275000
1&
#3280000
0&
#3285000
1&
#3290000
0&
#3295000
1&
#3300000
0&
#3305000
1&
#3310000
0&
#3315000
1&
#3320000
0&
#3325000
1&
#3330000
0&
#3335000
1&
#3340000
0&
#3345000
1&
#3350000
0&
0(
#3355000
1,
06
1&
#3360000
0&
#3365000
0,
07
1&
#3370000
0&
#3375000
1&
#3380000
0&
#3385000
1&
#3390000
0&
#3395000
1&
#3400000
0&
b11 @
#3405000
1&
#3410000
0&
#3415000
1&
#3420000
0&
#3425000
1&
#3430000
0&
#3435000
1&
#3440000
0&
#3445000
1&
#3450000
0&
#3455000
1&
#3460000
0&
#3465000
1&
#3470000
0&
#3475000
1&
#3480000
0&
#3485000
1&
#3490000
0&
#3495000
1&
#3500000
0&
1(
#3505000
1.
1-
16
1&
#3510000
0&
#3515000
0.
0-
17
b101 3
1&
#3520000
0&
#3525000
1&
#3530000
0&
#3535000
1&
#3540000
0&
#3545000
1&
#3550000
0&
#3555000
1&
#3560000
0&
#3565000
1&
#3570000
0&
#3575000
1&
#3580000
0&
#3585000
1&
#3590000
0&
#3595000
1&
#3600000
0&
0(
#3605000
1,
06
1&
#3610000
0&
#3615000
0,
07
1&
#3620000
0&
#3625000
1&
#3630000
0&
#3635000
1&
#3640000
0&
#3645000
1&
#3650000
0&
b10 @
#3655000
1&
#3660000
0&
#3665000
1&
#3670000
0&
#3675000
1&
#3680000
0&
#3685000
1&
#3690000
0&
#3695000
1&
#3700000
0&
#3705000
1&
#3710000
0&
#3715000
1&
#3720000
0&
#3725000
1&
#3730000
0&
#3735000
1&
#3740000
0&
#3745000
1&
#3750000
0&
1(
#3755000
1.
1-
16
1&
#3760000
0&
#3765000
0.
0-
b110 3
17
1&
#3770000
0&
#3775000
1&
#3780000
0&
#3785000
1&
#3790000
0&
#3795000
1&
#3800000
0&
#3805000
1&
#3810000
0&
#3815000
1&
#3820000
0&
#3825000
1&
#3830000
0&
#3835000
1&
#3840000
0&
#3845000
1&
#3850000
0&
0(
#3855000
1,
06
1&
#3860000
0&
#3865000
0,
07
1&
#3870000
0&
#3875000
1&
#3880000
0&
#3885000
1&
#3890000
0&
#3895000
1&
#3900000
0&
b1 @
#3905000
1&
#3910000
0&
#3915000
1&
#3920000
0&
#3925000
1&
#3930000
0&
#3935000
1&
#3940000
0&
#3945000
1&
#3950000
0&
#3955000
1&
#3960000
0&
#3965000
1&
#3970000
0&
#3975000
1&
#3980000
0&
#3985000
1&
#3990000
0&
#3995000
1&
#4000000
0&
1(
#4005000
1.
1-
16
1&
#4010000
0&
#4015000
0.
0-
17
b111 3
1&
#4020000
0&
#4025000
1&
#4030000
0&
#4035000
1&
#4040000
0&
#4045000
1&
#4050000
0&
#4055000
1&
#4060000
0&
#4065000
1&
#4070000
0&
#4075000
1&
#4080000
0&
#4085000
1&
#4090000
0&
#4095000
1&
#4100000
0&
0(
#4105000
1,
06
1&
#4110000
0&
#4115000
0,
07
1&
#4120000
0&
#4125000
1&
#4130000
0&
#4135000
1&
#4140000
0&
#4145000
1&
#4150000
0&
b0 @
#4155000
1&
#4160000
0&
#4165000
1&
#4170000
0&
#4175000
1&
#4180000
0&
#4185000
1&
#4190000
0&
#4195000
1&
#4200000
0&
#4205000
1&
#4210000
0&
#4215000
1&
#4220000
0&
#4225000
1&
#4230000
0&
#4235000
1&
#4240000
0&
#4245000
1&
#4250000
0&
1(
#4255000
1.
1-
16
1&
#4260000
0&
#4265000
0.
0-
b100 ;
b1000 3
17
1&
#4270000
0&
#4275000
1&
#4280000
0&
#4285000
1&
#4290000
0&
#4295000
1&
#4300000
0&
#4305000
1&
#4310000
0&
#4315000
1&
#4320000
0&
#4325000
1&
#4330000
0&
#4335000
1&
#4340000
0&
#4345000
1&
#4350000
0&
0(
#4355000
1,
06
1&
#4360000
0&
#4365000
0,
1$
07
1&
#4370000
0&
#4375000
1&
#4380000
0&
#4385000
1&
#4390000
0&
#4395000
1&
#4400000
0&
1(
1)
b11111111111111111111111111111111 @
#4405000
1-
18
16
1&
#4410000
0&
#4415000
0-
19
17
1&
#4420000
0&
#4425000
1&
#4430000
0&
#4435000
1&
#4440000
0&
#4445000
1&
#4450000
0&
#4455000
1&
#4460000
0&
#4465000
1&
#4470000
0&
#4475000
1&
#4480000
0&
#4485000
1&
#4490000
0&
#4495000
1&
#4500000
0&
0(
#4505000
1,
06
1&
#4510000
0&
#4515000
0,
07
b0 3
b101 ;
0$
1&
#4520000
0&
#4525000
1&
#4530000
0&
#4535000
1&
#4540000
0&
#4545000
1&
#4550000
0&
b111 @
b1010 ?
#4555000
1&
#4560000
0&
#4565000
1&
#4570000
0&
#4575000
1&
#4580000
0&
#4585000
1&
#4590000
0&
#4595000
1&
#4600000
0&
0)
#4605000
08
1&
#4610000
0&
#4615000
09
1&
#4620000
0&
#4625000
1&
#4630000
0&
#4635000
1&
#4640000
0&
#4645000
1&
#4650000
0&
1(
#4655000
1.
1-
16
1&
#4660000
0&
#4665000
0.
0-
b1 3
17
1&
#4670000
0&
#4675000
1&
#4680000
0&
#4685000
1&
#4690000
0&
#4695000
1&
#4700000
0&
#4705000
1&
#4710000
0&
#4715000
1&
#4720000
0&
#4725000
1&
#4730000
0&
#4735000
1&
#4740000
0&
#4745000
1&
#4750000
0&
0(
#4755000
1,
06
1&
#4760000
0&
#4765000
0,
07
1&
#4770000
0&
#4775000
1&
#4780000
0&
#4785000
1&
#4790000
0&
#4795000
1&
#4800000
0&
b110 @
#4805000
1&
#4810000
0&
#4815000
1&
#4820000
0&
#4825000
1&
#4830000
0&
#4835000
1&
#4840000
0&
#4845000
1&
#4850000
0&
#4855000
1&
#4860000
0&
#4865000
1&
#4870000
0&
#4875000
1&
#4880000
0&
#4885000
1&
#4890000
0&
#4895000
1&
#4900000
0&
1(
#4905000
1.
1-
16
1&
#4910000
0&
#4915000
0.
0-
17
b10 3
1&
#4920000
0&
#4925000
1&
#4930000
0&
#4935000
1&
#4940000
0&
#4945000
1&
#4950000
0&
#4955000
1&
#4960000
0&
#4965000
1&
#4970000
0&
#4975000
1&
#4980000
0&
#4985000
1&
#4990000
0&
#4995000
1&
#5000000
0&
0(
#5005000
1,
06
1&
#5010000
0&
