src/digital/main_event_counter.v
module main_event_counter (
    input  wire       clk,
    input  wire       en,
    input  wire       pulse_in,      // from pulse generator
    input  wire       timeout_rst,   // signal from timeout counter
    input  wire [7:0] threshold,     // from I2C Config
    output wire       trigger_out,   // signal successful reaching target
    output wire [7:0] count_reg      // for internal monitoring
);

    // Internal counter to keep track of the number of pulses received
    reg [7:0] current_count;
    wire auto_reset = (current_count == threshold) && (threshold != 8'h00);
    
    // Meneruskan sinyal komparator langsung ke luar sebagai output
    assign trigger_out = auto_reset;
    assign count_reg   = current_count;

    always @(posedge clk or posedge en) begin
        if (en) begin
            current_count <= 8'h00;

        end else begin
            if (timeout_rst || auto_reset) begin
                current_count <= 8'h00;
            end 
            else if (pulse_in) begin
                current_count <= current_count + 1'b1;
            end
        end
    end

endmodule

src/digital/timeout_counter.v
module timeout_counter (
    input  wire       clk,
    input  wire       en,
    input  wire       pulse_in,      // from pulse generator
    input  wire [7:0] timeout_val,   // timeout value from I2C Config
    output wire       timeout_rst    // signal to reset main_event_counter when timeout occurs
);

    reg [7:0] timer_count; //8-bit state register for counting clock cycles
    wire auto_reset = (timer_count >= timeout_val) && (timeout_val != 8'h00); // comparator block to check if timer_count has reached timeout_val
    assign timeout_rst = auto_reset;

    always @(posedge clk or posedge en) begin
        if (en) begin
            timer_count <= 8'h00;
        end else begin
            // reset if pulse_in is high or auto_reset is high (priority 1)
            if (pulse_in || auto_reset) begin
                timer_count <= 8'h00;
            end 
            // increment timer_count if no reset conditions are met (priority 2)
            else begin
                timer_count <= timer_count + 1'b1;
            end
        end
    end

endmodule

src/digital/i2c_slave_config.v
module i2c_slave_config #(
    parameter SLAVE_ADDR = 7'h50
)(
    input  wire       clk,           
    input  wire       en,
    input  wire       scl,
    input  wire       sda_in,
    output reg        sda_out,       
    output reg        sda_oe,        
    output wire [7:0] threshold_reg,
    output wire [7:0] timeout_reg,
    output wire [7:0] capacitor_ctrl_reg
);

    // Block 1: edge detection for SCL and SDA
    reg scl_d1, scl_d2, sda_d1, sda_d2;
    always @(posedge clk or posedge en) begin
        if (en) begin
            scl_d1 <= 1'b1; scl_d2 <= 1'b1;
            sda_d1 <= 1'b1; sda_d2 <= 1'b1;
        end else begin
            scl_d1 <= scl;     scl_d2 <= scl_d1;
            sda_d1 <= sda_in;  sda_d2 <= sda_d1;
        end
    end

    wire scl_rise  = scl_d1 & ~scl_d2;
    wire scl_fall  = ~scl_d1 & scl_d2;
    wire start_det = scl_d1 & scl_d2 & ~sda_d1 & sda_d2;
    wire stop_det  = scl_d1 & scl_d2 & sda_d1 & ~sda_d2;

    // Block 2: FSM States 
    localparam IDLE = 3'd0, ADDR = 3'd1, ADDR_ACK = 3'd2, REGADDR = 3'd3, REGADDR_ACK = 3'd4, DATA = 3'd5, DATA_ACK = 3'd6;

    reg [2:0] state;
    reg [3:0] bit_cnt;
    reg       write_en;

    wire shift_en = (state == ADDR || state == REGADDR || state == DATA) && scl_rise;

    always @(posedge clk or posedge en) begin
        if (en) begin
            state <= IDLE; 
            bit_cnt <= 4'd0; 
            sda_out <= 1'b1; 
            sda_oe <= 1'b0; 
            write_en <= 1'b0;
        end else begin
            write_en <= 1'b0; // Default: clear flag write_en

            if (start_det) begin 
                state <= ADDR; 
                bit_cnt <= 4'd0; 
                sda_oe <= 1'b0; 
            end 
            else if (stop_det) begin 
                state <= IDLE; 
                sda_oe <= 1'b0; 
            end 
            else begin
                case (state)
                    ADDR: begin
                        if (shift_en) begin
                            bit_cnt <= bit_cnt + 1'b1;
                            if (bit_cnt == 4'd7) state <= ADDR_ACK;
                        end
                    end
                    
                    ADDR_ACK: begin
                        if (scl_fall) begin
                            if (sda_oe == 1'b0) begin
                                // scl fall 9 check: if address matches and R/W bit is 0 (write), then ACK
                                if (parallel_data[7:1] == SLAVE_ADDR && parallel_data[0] == 1'b0) begin
                                    sda_out <= 1'b0; 
                                    sda_oe <= 1'b1; 
                                end else begin
                                    state <= IDLE; // NACK, wrong address or R/W bit is 1 (read), go back to IDLE
                                end
                            end else begin
                                // scl fall 10: release SDA and move to REGADDR state
                                sda_oe <= 1'b0;
                                state <= REGADDR;
                                bit_cnt <= 4'd0;
                            end
                        end
                    end

                    REGADDR: begin
                        if (shift_en) begin
                            bit_cnt <= bit_cnt + 1'b1;
                            if (bit_cnt == 4'd7) state <= REGADDR_ACK;
                        end
                    end
                    
                    REGADDR_ACK: begin
                        if (scl_fall) begin
                            if (sda_oe == 1'b0) begin
                                sda_out <= 1'b0; 
                                sda_oe <= 1'b1; 
                            end else begin
                                sda_oe <= 1'b0; 
                                state <= DATA;
                                bit_cnt <= 4'd0;
                            end
                        end
                    end

                    DATA: begin
                        if (shift_en) begin
                            bit_cnt <= bit_cnt + 1'b1;
                            if (bit_cnt == 4'd7) state <= DATA_ACK;
                        end
                    end

                    DATA_ACK: begin
                        if (scl_fall) begin
                            if (sda_oe == 1'b0) begin
                                sda_out <= 1'b0; 
                                sda_oe <= 1'b1; 
                                write_en <= 1'b1; // Trigger write_en to indicate that a full byte has been received and should be written to the appropriate register
                            end else begin
                                sda_oe <= 1'b0; 
                                state <= DATA; // Loop back to DATA state for next byte
                                bit_cnt <= 4'd0;
                            end
                        end
                    end
                    
                    default: state <= IDLE;
                endcase
            end
        end
    end

    // Block 3: Shift Register 
    reg [7:0] shift_reg_internal;
    reg [1:0] reg_addr;
    wire [7:0] parallel_data = shift_reg_internal;

    always @(posedge clk or posedge en) begin
        if (en) begin
            shift_reg_internal <= 8'h00;
            reg_addr           <= 2'b00;
        end else begin
            if (shift_en) begin
                shift_reg_internal <= {shift_reg_internal[6:0], sda_d1};
            end
            
            // Simpan alamat register tepat di SCL fall ke-8 saat REGADDR_ACK
            if (state == REGADDR_ACK && scl_fall && sda_oe == 1'b0) begin
                reg_addr <= shift_reg_internal[1:0];
            end
        end
    end

    // Block 4: Decoder & Registers
    // Register Map:
    // 0x00: threshold_reg (default: 0x05)
    // 0x01: timeout_reg (default: 0xA0)
    // 0x02: capacitor_ctrl_reg (default: 0x00)
    // 0x03: reserved for future use
    
    reg [7:0] threshold_int, timeout_int, capacitor_ctrl_int;
    assign threshold_reg      = threshold_int;
    assign timeout_reg        = timeout_int;
    assign capacitor_ctrl_reg = capacitor_ctrl_int;

    always @(posedge clk or posedge en) begin
        if (en) begin
            threshold_int       <= 8'h05; 
            timeout_int         <= 8'hA0;
            capacitor_ctrl_int  <= 8'h00;
        end else if (write_en) begin
            case (reg_addr)
                2'b00: threshold_int       <= parallel_data;
                2'b01: timeout_int         <= parallel_data;
                2'b10: capacitor_ctrl_int  <= parallel_data;
                default: ; // Reserved register, do nothing
            endcase
        end
    end
endmodule

src/digital/pulse_generator.v
module pulse_generator (
    input wire clk,
    input wire en,
    input wire signal_in, // input signal from comparator
    output wire pulse_out // output pulse
);
    reg signal_d1;
    reg signal_d2;

    always @(posedge clk or posedge en) begin
        if (en) begin
            signal_d1 <= 1'b0;
            signal_d2 <= 1'b0;  
        end else begin
            signal_d1 <= signal_in; 
            signal_d2 <= signal_d1; 
        end
    end

    assign pulse_out = signal_d1 & ~signal_d2; // pulse in transition high low
endmodule

src/digital/top.v
module top #(
    parameter SLAVE_ADDR = 7'h50
)(
    // clock signal and Global Reset
    input  wire       clk,
    input  wire       en,
    input  wire       signal_in,   
    
    // I2C Configuration Interface
    input  wire       scl,
    input  wire       sda_in,
    output wire       sda_out,
    output wire       sda_oe,
    
    // Output digital
    output wire       trigger_out, 
    output wire [7:0] count_reg,
    
    // Capacitor Control Output
    output wire [7:0] capacitor_ctrl
);


    wire       pulse_w;
    wire       timeout_rst_w;
    wire [7:0] threshold_w;
    wire [7:0] timeout_val_w;
    wire [7:0] capacitor_ctrl_w;

    // 1. Pulse Generator
    pulse_generator u_pulse_gen (
        .clk       (clk),
        .en        (en),
        .signal_in (signal_in),
        .pulse_out (pulse_w)
    );

    // 2. I2C Slave Configuration
    i2c_slave_config #(
        .SLAVE_ADDR(SLAVE_ADDR)
    ) u_i2c_config (
        .clk                (clk),
        .en                 (en),
        .scl                (scl),
        .sda_in             (sda_in),
        .sda_out            (sda_out),
        .sda_oe             (sda_oe),
        .threshold_reg      (threshold_w),
        .timeout_reg        (timeout_val_w),
        .capacitor_ctrl_reg (capacitor_ctrl_w)
    );
    
    // Connect capacitor control to output
    assign capacitor_ctrl = capacitor_ctrl_w;

    // 3. Timeout Counter
    timeout_counter u_timeout_cnt (
        .clk         (clk),
        .en          (en),
        .pulse_in    (pulse_w),
        .timeout_val (timeout_val_w),
        .timeout_rst (timeout_rst_w)
    );

    // 4. Main Event Counter
    wire trigger_internal;
    main_event_counter u_main_cnt (
        .clk         (clk),
        .en          (en),
        .pulse_in    (pulse_w),
        .timeout_rst (timeout_rst_w),
        .threshold   (threshold_w),
        .trigger_out (trigger_internal),
        .count_reg   (count_reg)
    );

    // 5. Bypass Logic
    // When en=1: bypass mode, output directly from comparator (signal_in)
    // When en=0: normal mode, output from digital processing (trigger_internal)
    assign trigger_out = en ? signal_in : trigger_internal;

endmodule

src/digital/tb/tb_top.v
`timescale 1ns / 1ps

module tb_top;
    parameter CLK_PERIOD = 10; 
    parameter SLAVE_ADDR = 7'h50;

    reg  clk;
    reg  en;
    reg  signal_in;
    
    // I2C Signals
    reg  scl;
    reg  sda_in;
    wire sda_out;
    wire sda_oe;
    
    // Output Monitoring
    wire       trigger_out;
    wire [7:0] count_reg;

    top #(
        .SLAVE_ADDR(SLAVE_ADDR)
    ) dut (
        .clk        (clk),
        .en         (en),
        .signal_in  (signal_in),
        .scl        (scl),
        .sda_in     (sda_in),
        .sda_out    (sda_out),
        .sda_oe     (sda_oe),
        .trigger_out(trigger_out),
        .count_reg  (count_reg)
    );

    always #(CLK_PERIOD/2) clk = ~clk;
    
    // task for sending a byte over I2C
    task i2c_write_byte(input [7:0] data);
        integer i;
        begin
            for (i = 7; i >= 0; i = i - 1) begin
                scl = 0; #50;
                sda_in = data[i]; #50;
                scl = 1; #100; 
                scl = 0; #50;
            end
            // ACK Phase
            sda_in = 1; scl = 1; #100; scl = 0; #50;
        end
    endtask

    // Task for writing a complete register (START -> ADDR -> REG -> DATA -> STOP)
    task i2c_write_reg(input [7:0] reg_addr, input [7:0] data);
        begin
            $display("[%0t ns] I2C Write -> Reg 0x%h = 0x%h", $time, reg_addr, data);
            // START
            sda_in = 0; #50; scl = 0; 
            // DEVICE ADDR (0x50 << 1 | 0 = 0xA0)
            i2c_write_byte(8'hA0); 
            // REGISTER ADDR
            i2c_write_byte(reg_addr);
            // DATA BYTE
            i2c_write_byte(data);
            // STOP
            scl = 0; sda_in = 0; #50;
            scl = 1; #50; sda_in = 1; #100;
        end
    endtask

    // Task for generating pulse from outside (simulating analog comparator)
    task send_external_pulse;
        begin
            // Duration of the pulse is arbitrary, as long as it exceeds 1 clock cycle (so it's read by d1 & d2)
            signal_in = 1'b1;
            #(CLK_PERIOD * 3); 
            signal_in = 1'b0;
            #(CLK_PERIOD * 3); // Jeda setelah pulsa
        end
    endtask

// main testbench sequence
    initial begin
        // Setup GTKWave
        $dumpfile("tb/vcd_file/tb_top.vcd");
        $dumpvars(0, tb_top);

        // 1. initialization
        clk = 0; en = 1; signal_in = 0; 
        scl = 1; sda_in = 1;
        
        #100 en = 0; #100;
        $display("\n=== Start ===\n");
        // 2. FASE KONFIGURASI (Via I2C)
        // Reg 0x00 = Threshold. Kita set ke 3.
        i2c_write_reg(8'h00, 8'h03);
        #200;
        // Reg 0x01 = Timeout. Kita set ke 20 siklus clock (0x14).
        i2c_write_reg(8'h01, 8'h14);
        #200;

        // 3. scenario 1: Test Threshold
        $display("\n=== Scenario 1: Test Threshold (Target: 3) ===");
        $display("[%0t ns] Send pulse 1", $time);
        send_external_pulse();
        
        $display("[%0t ns] Send pulse 2", $time);
        send_external_pulse();
        
        $display("[%0t ns] Send pulse 3 (trigger!)", $time);
        send_external_pulse();
        
        #5; 
        if (trigger_out) $display("SUCCESS: trigger_out turned on!");
        else $display("FAILED: trigger_out did not turn on!");
        #50;

        // 4. scenario 2: Test Timeout
        $display("\n=== Scenario 2: Test Timeout (Batas: 20 cycles = 200ns) ===");
        $display("[%0t ns] Send 1 new pulse", $time);
        send_external_pulse();
        $display("[%0t ns] Current value of count_reg: %d", $time, count_reg);
        
        $display("[%0t ns] Waiting for 300ns (Exceeding Timeout)...", $time);
        #300; // Tunggu 30 siklus clock
        
        if (count_reg == 8'h00) $display("SUCCESS: count_reg successfully reset by Timeout!");
        else $display("FAILED: count_reg failed to reset! Current value: %d", count_reg);

        // 5. SELESAI
        $display("\n=== SIMULASI SELESAI ===");
        #100;
        $finish;
    end

endmodule

src/digital/tb/vcd_file/tb_top.vcd
$date
	Mon Aug 24 09:03:37 2026
$end
$version
	Icarus Verilog
$end
$timescale
	1ps
$end
$scope module tb_top $end
$var wire 1 ! trigger_out $end
$var wire 1 " sda_out $end
$var wire 1 # sda_oe $end
$var wire 8 $ count_reg [7:0] $end
$var reg 1 % clk $end
$var reg 1 & en $end
$var reg 1 ' scl $end
$var reg 1 ( sda_in $end
$var reg 1 ) signal_in $end
$scope module dut $end
$var wire 8 * capacitor_ctrl [7:0] $end
$var wire 1 % clk $end
$var wire 1 & en $end
$var wire 1 ' scl $end
$var wire 1 ( sda_in $end
$var wire 1 ) signal_in $end
$var wire 1 ! trigger_out $end
$var wire 1 + trigger_internal $end
$var wire 8 , timeout_val_w [7:0] $end
$var wire 1 - timeout_rst_w $end
$var wire 8 . threshold_w [7:0] $end
$var wire 1 " sda_out $end
$var wire 1 # sda_oe $end
$var wire 1 / pulse_w $end
$var wire 8 0 count_reg [7:0] $end
$var wire 8 1 capacitor_ctrl_w [7:0] $end
$scope module u_i2c_config $end
$var wire 8 2 capacitor_ctrl_reg [7:0] $end
$var wire 1 % clk $end
$var wire 1 & en $end
$var wire 8 3 parallel_data [7:0] $end
$var wire 1 ' scl $end
$var wire 1 4 scl_fall $end
$var wire 1 5 scl_rise $end
$var wire 1 ( sda_in $end
$var wire 1 6 shift_en $end
$var wire 1 7 start_det $end
$var wire 1 8 stop_det $end
$var wire 8 9 threshold_reg [7:0] $end
$var wire 8 : timeout_reg [7:0] $end
$var reg 4 ; bit_cnt [3:0] $end
$var reg 8 < capacitor_ctrl_int [7:0] $end
$var reg 2 = reg_addr [1:0] $end
$var reg 1 > scl_d1 $end
$var reg 1 ? scl_d2 $end
$var reg 1 @ sda_d1 $end
$var reg 1 A sda_d2 $end
$var reg 1 # sda_oe $end
$var reg 1 " sda_out $end
$var reg 8 B shift_reg_internal [7:0] $end
$var reg 3 C state [2:0] $end
$var reg 8 D threshold_int [7:0] $end
$var reg 8 E timeout_int [7:0] $end
$var reg 1 F write_en $end
$upscope $end
$scope module u_main_cnt $end
$var wire 1 G auto_reset $end
$var wire 1 % clk $end
$var wire 8 H count_reg [7:0] $end
$var wire 1 & en $end
$var wire 8 I threshold [7:0] $end
$var wire 1 + trigger_out $end
$var wire 1 - timeout_rst $end
$var wire 1 / pulse_in $end
$var reg 8 J current_count [7:0] $end
$upscope $end
$scope module u_pulse_gen $end
$var wire 1 % clk $end
$var wire 1 & en $end
$var wire 1 / pulse_out $end
$var wire 1 ) signal_in $end
$var reg 1 K signal_d1 $end
$var reg 1 L signal_d2 $end
$upscope $end
$scope module u_timeout_cnt $end
$var wire 1 M auto_reset $end
$var wire 1 % clk $end
$var wire 1 & en $end
$var wire 1 / pulse_in $end
$var wire 1 - timeout_rst $end
$var wire 8 N timeout_val [7:0] $end
$var reg 8 O timer_count [7:0] $end
$upscope $end
$upscope $end
$scope task i2c_write_byte $end
$var reg 8 P data [7:0] $end
$var integer 32 Q i [31:0] $end
$upscope $end
$scope task i2c_write_reg $end
$var reg 8 R data [7:0] $end
$var reg 8 S reg_addr [7:0] $end
$upscope $end
$scope task send_external_pulse $end
$upscope $end
$upscope $end
$enddefinitions $end
#0
$dumpvars
bx S
bx R
bx Q
bx P
b0 O
b10100000 N
0M
0L
0K
b0 J
b101 I
b0 H
0G
0F
b10100000 E
b101 D
b0 C
b0 B
1A
1@
1?
1>
b0 =
b0 <
b0 ;
b10100000 :
b101 9
08
07
06
05
04
b0 3
b0 2
b0 1
b0 0
0/
b101 .
0-
b10100000 ,
0+
b0 *
0)
1(
1'
1&
0%
b0 $
0#
1"
0!
$end
#5000
1%
#10000
0%
#15000
1%
#20000
0%
#25000
1%
#30000
0%
#35000
1%
#40000
0%
#45000
1%
#50000
0%
#55000
1%
#60000
0%
#65000
1%
#70000
0%
#75000
1%
#80000
0%
#85000
1%
#90000
0%
#95000
1%
#100000
0%
0&
#105000
b1 O
1%
#110000
0%
#115000
b10 O
1%
#120000
0%
#125000
b11 O
1%
#130000
0%
#135000
b100 O
1%
#140000
0%
#145000
b101 O
1%
#150000
0%
#155000
b110 O
1%
#160000
0%
#165000
b111 O
1%
#170000
0%
#175000
b1000 O
1%
#180000
0%
#185000
b1001 O
1%
#190000
0%
#195000
b1010 O
1%
#200000
0%
0(
b11 R
b0 S
#205000
17
b1011 O
0@
1%
#210000
0%
#215000
07
0A
b1 C
b1100 O
1%
#220000
0%
#225000
b1101 O
1%
#230000
0%
#235000
b1110 O
1%
#240000
0%
#245000
b1111 O
1%
#250000
0%
b111 Q
b10100000 P
0'
#255000
14
0>
b10000 O
1%
#260000
0%
#265000
04
b10001 O
0?
1%
#270000
0%
#275000
b10010 O
1%
#280000
0%
#285000
b10011 O
1%
#290000
0%
#295000
b10100 O
1%
#300000
0%
1(
#305000
b10101 O
1@
1%
#310000
0%
#315000
1A
b10110 O
1%
#320000
0%
#325000
b10111 O
1%
#330000
0%
#335000
b11000 O
1%
#340000
0%
#345000
b11001 O
1%
#350000
0%
1'
#355000
16
15
1>
b11010 O
1%
#360000
0%
#365000
06
05
b11011 O
b1 3
b1 B
b1 ;
1?
1%
#370000
0%
#375000
b11100 O
1%
#380000
0%
#385000
b11101 O
1%
#390000
0%
#395000
b11110 O
1%
#400000
0%
#405000
b11111 O
1%
#410000
0%
#415000
b100000 O
1%
#420000
0%
#425000
b100001 O
1%
#430000
0%
#435000
b100010 O
1%
#440000
0%
#445000
b100011 O
1%
#450000
0%
0'
#455000
14
0>
b100100 O
1%
#460000
0%
#465000
04
b100101 O
0?
1%
#470000
0%
#475000
b100110 O
1%
#480000
0%
#485000
b100111 O
1%
#490000
0%
#495000
b101000 O
1%
#500000
0%
b110 Q
#505000
b101001 O
1%
#510000
0%
#515000
b101010 O
1%
#520000
0%
#525000
b101011 O
1%
#530000
0%
#535000
b101100 O
1%
#540000
0%
#545000
b101101 O
1%
#550000
0%
0(
#555000
0@
b101110 O
1%
#560000
0%
#565000
b101111 O
0A
1%
#570000
0%
#575000
b110000 O
1%
#580000
0%
#585000
b110001 O
1%
#590000
0%
#595000
b110010 O
1%
#600000
0%
1'
#605000
16
15
b110011 O
1>
1%
#610000
0%
#615000
06
05
1?
b10 ;
b10 3
b10 B
b110100 O
1%
#620000
0%
#625000
b110101 O
1%
#630000
0%
#635000
b110110 O
1%
#640000
0%
#645000
b110111 O
1%
#650000
0%
#655000
b111000 O
1%
#660000
0%
#665000
b111001 O
1%
#670000
0%
#675000
b111010 O
1%
#680000
0%
#685000
b111011 O
1%
#690000
0%
#695000
b111100 O
1%
#700000
0%
0'
#705000
14
b111101 O
0>
1%
#710000
0%
#715000
04
0?
b111110 O
1%
#720000
0%
#725000
b111111 O
1%
#730000
0%
#735000
b1000000 O
1%
#740000
0%
#745000
b1000001 O
1%
#750000
0%
b101 Q
#755000
b1000010 O
1%
#760000
0%
#765000
b1000011 O
1%
#770000
0%
#775000
b1000100 O
1%
#780000
0%
#785000
b1000101 O
1%
#790000
0%
#795000
b1000110 O
1%
#800000
0%
1(
#805000
b1000111 O
1@
1%
#810000
0%
#815000
1A
b1001000 O
1%
#820000
0%
#825000
b1001001 O
1%
#830000
0%
#835000
b1001010 O
1%
#840000
0%
#845000
b1001011 O
1%
#850000
0%
1'
#855000
16
15
1>
b1001100 O
1%
#860000
0%
#865000
06
05
b1001101 O
b101 3
b101 B
b11 ;
1?
1%
#870000
0%
#875000
b1001110 O
1%
#880000
0%
#885000
b1001111 O
1%
#890000
0%
#895000
b1010000 O
1%
#900000
0%
#905000
b1010001 O
1%
#910000
0%
#915000
b1010010 O
1%
#920000
0%
#925000
b1010011 O
1%
#930000
0%
#935000
b1010100 O
1%
#940000
0%
#945000
b1010101 O
1%
#950000
0%
0'
#955000
14
0>
b1010110 O
1%
#960000
0%
#965000
04
b1010111 O
0?
1%
#970000
0%
#975000
b1011000 O
1%
#980000
0%
#985000
b1011001 O
1%
#990000
0%
#995000
b1011010 O
1%
#1000000
0%
b100 Q
#1005000
b1011011 O
1%
#1010000
0%
#1015000
b1011100 O
1%
#1020000
0%
#1025000
b1011101 O
1%
#1030000
0%
#1035000
b1011110 O
1%
#1040000
0%
#1045000
b1011111 O
1%
#1050000
0%
0(
#1055000
0@
b1100000 O
1%
#1060000
0%
#1065000
b1100001 O
0A
1%
#1070000
0%
#1075000
b1100010 O
1%
#1080000
0%
#1085000
b1100011 O
1%
#1090000
0%
#1095000
b1100100 O
1%
#1100000
0%
1'
#1105000
16
15
b1100101 O
1>
1%
#1110000
0%
#1115000
06
05
1?
b100 ;
b1010 3
b1010 B
b1100110 O
1%
#1120000
0%
#1125000
b1100111 O
1%
#1130000
0%
#1135000
b1101000 O
1%
#1140000
0%
#1145000
b1101001 O
1%
#1150000
0%
#1155000
b1101010 O
1%
#1160000
0%
#1165000
b1101011 O
1%
#1170000
0%
#1175000
b1101100 O
1%
#1180000
0%
#1185000
b1101101 O
1%
#1190000
0%
#1195000
b1101110 O
1%
#1200000
0%
0'
#1205000
14
b1101111 O
0>
1%
#1210000
0%
#1215000
04
0?
b1110000 O
1%
#1220000
0%
#1225000
b1110001 O
1%
#1230000
0%
#1235000
b1110010 O
1%
#1240000
0%
#1245000
b1110011 O
1%
#1250000
0%
b11 Q
#1255000
b1110100 O
1%
#1260000
0%
#1265000
b1110101 O
1%
#1270000
0%
#1275000
b1110110 O
1%
#1280000
0%
#1285000
b1110111 O
1%
#1290000
0%
#1295000
b1111000 O
1%
#1300000
0%
#1305000
b1111001 O
1%
#1310000
0%
#1315000
b1111010 O
1%
#1320000
0%
#1325000
b1111011 O
1%
#1330000
0%
#1335000
b1111100 O
1%
#1340000
0%
#1345000
b1111101 O
1%
#1350000
0%
1'
#1355000
16
15
1>
b1111110 O
1%
#1360000
0%
#1365000
06
05
b1111111 O
b10100 3
b10100 B
b101 ;
1?
1%
#1370000
0%
#1375000
b10000000 O
1%
#1380000
0%
#1385000
b10000001 O
1%
#1390000
0%
#1395000
b10000010 O
1%
#1400000
0%
#1405000
b10000011 O
1%
#1410000
0%
#1415000
b10000100 O
1%
#1420000
0%
#1425000
b10000101 O
1%
#1430000
0%
#1435000
b10000110 O
1%
#1440000
0%
#1445000
b10000111 O
1%
#1450000
0%
0'
#1455000
14
0>
b10001000 O
1%
#1460000
0%
#1465000
04
b10001001 O
0?
1%
#1470000
0%
#1475000
b10001010 O
1%
#1480000
0%
#1485000
b10001011 O
1%
#1490000
0%
#1495000
b10001100 O
1%
#1500000
0%
b10 Q
#1505000
b10001101 O
1%
#1510000
0%
#1515000
b10001110 O
1%
#1520000
0%
#1525000
b10001111 O
1%
#1530000
0%
#1535000
b10010000 O
1%
#1540000
0%
#1545000
b10010001 O
1%
#1550000
0%
#1555000
b10010010 O
1%
#1560000
0%
#1565000
b10010011 O
1%
#1570000
0%
#1575000
b10010100 O
1%
#1580000
0%
#1585000
b10010101 O
1%
#1590000
0%
#1595000
b10010110 O
1%
#1600000
0%
1'
#1605000
16
15
b10010111 O
1>
1%
#1610000
0%
#1615000
06
05
1?
b110 ;
b101000 3
b101000 B
b10011000 O
1%
#1620000
0%
#1625000
b10011001 O
1%
#1630000
0%
#1635000
b10011010 O
1%
#1640000
0%
#1645000
b10011011 O
1%
#1650000
0%
#1655000
b10011100 O
1%
#1660000
0%
#1665000
b10011101 O
1%
#1670000
0%
#1675000
b10011110 O
1%
#1680000
0%
#1685000
b10011111 O
1%
#1690000
0%
#1695000
1-
1M
b10100000 O
1%
#1700000
0%
0'
#1705000
14
0-
0M
b0 O
0>
1%
#1710000
0%
#1715000
04
0?
b1 O
1%
#1720000
0%
#1725000
b10 O
1%
#1730000
0%
#1735000
b11 O
1%
#1740000
0%
#1745000
b100 O
1%
#1750000
0%
b1 Q
#1755000
b101 O
1%
#1760000
0%
#1765000
b110 O
1%
#1770000
0%
#1775000
b111 O
1%
#1780000
0%
#1785000
b1000 O
1%
#1790000
0%
#1795000
b1001 O
1%
#1800000
0%
#1805000
b1010 O
1%
#1810000
0%
#1815000
b1011 O
1%
#1820000
0%
#1825000
b1100 O
1%
#1830000
0%
#1835000
b1101 O
1%
#1840000
0%
#1845000
b1110 O
1%
#1850000
0%
1'
#1855000
16
15
1>
b1111 O
1%
#1860000
0%
#1865000
06
05
b10000 O
b1010000 3
b1010000 B
b111 ;
1?
1%
#1870000
0%
#1875000
b10001 O
1%
#1880000
0%
#1885000
b10010 O
1%
#1890000
0%
#1895000
b10011 O
1%
#1900000
0%
#1905000
b10100 O
1%
#1910000
0%
#1915000
b10101 O
1%
#1920000
0%
#1925000
b10110 O
1%
#1930000
0%
#1935000
b10111 O
1%
#1940000
0%
#1945000
b11000 O
1%
#1950000
0%
0'
#1955000
14
0>
b11001 O
1%
#1960000
0%
#1965000
04
b11010 O
0?
1%
#1970000
0%
#1975000
b11011 O
1%
#1980000
0%
#1985000
b11100 O
1%
#1990000
0%
#1995000
b11101 O
1%
#2000000
0%
b0 Q
#2005000
b11110 O
1%
#2010000
0%
#2015000
b11111 O
1%
#2020000
0%
#2025000
b100000 O
1%
#2030000
0%
#2035000
b100001 O
1%
#2040000
0%
#2045000
b100010 O
1%
#2050000
0%
#2055000
b100011 O
1%
#2060000
0%
#2065000
b100100 O
1%
#2070000
0%
#2075000
b100101 O
1%
#2080000
0%
#2085000
b100110 O
1%
#2090000
0%
#2095000
b100111 O
1%
#2100000
0%
1'
#2105000
16
15
b101000 O
1>
1%
#2110000
0%
#2115000
06
05
1?
b10 C
b1000 ;
b10100000 3
b10100000 B
b101001 O
1%
#2120000
0%
#2125000
b101010 O
1%
#2130000
0%
#2135000
b101011 O
1%
#2140000
0%
#2145000
b101100 O
1%
#2150000
0%
#2155000
b101101 O
1%
#2160000
0%
#2165000
b101110 O
1%
#2170000
0%
#2175000
b101111 O
1%
#2180000
0%
#2185000
b110000 O
1%
#2190000
0%
#2195000
b110001 O
1%
#2200000
0%
0'
#2205000
14
b110010 O
0>
1%
#2210000
0%
#2215000
04
0?
1#
0"
b110011 O
1%
#2220000
0%
#2225000
b110100 O
1%
#2230000
0%
#2235000
b110101 O
1%
#2240000
0%
#2245000
b110110 O
1%
#2250000
0%
1'
1(
b11111111111111111111111111111111 Q
#2255000
15
1@
1>
b110111 O
1%
#2260000
0%
#2265000
05
b111000 O
1A
1?
1%
#2270000
0%
#2275000
b111001 O
1%
#2280000
0%
#2285000
b111010 O
1%
#2290000
0%
#2295000
b111011 O
1%
#2300000
0%
#2305000
b111100 O
1%
#2310000
0%
#2315000
b111101 O
1%
#2320000
0%
#2325000
b111110 O
1%
#2330000
0%
#2335000
b111111 O
1%
#2340000
0%
#2345000
b1000000 O
1%
#2350000
0%
0'
#2355000
14
0>
b1000001 O
1%
#2360000
0%
#2365000
04
b1000010 O
b0 ;
b11 C
0#
0?
1%
#2370000
0%
#2375000
b1000011 O
1%
#2380000
0%
#2385000
b1000100 O
1%
#2390000
0%
#2395000
b1000101 O
1%
#2400000
0%
b111 Q
b0 P
#2405000
b1000110 O
1%
#2410000
0%
#2415000
b1000111 O
1%
#2420000
0%
#2425000
b1001000 O
1%
#2430000
0%
#2435000
b1001001 O
1%
#2440000
0%
#2445000
b1001010 O
1%
#2450000
0%
0(
#2455000
0@
b1001011 O
1%
#2460000
0%
#2465000
b1001100 O
0A
1%
#2470000
0%
#2475000
b1001101 O
1%
#2480000
0%
#2485000
b1001110 O
1%
#2490000
0%
#2495000
b1001111 O
1%
#2500000
0%
1'
#2505000
16
15
b1010000 O
1>
1%
#2510000
0%
#2515000
06
05
1?
b1 ;
b1000000 3
b1000000 B
b1010001 O
1%
#2520000
0%
#2525000
b1010010 O
1%
#2530000
0%
#2535000
b1010011 O
1%
#2540000
0%
#2545000
b1010100 O
1%
#2550000
0%
#2555000
b1010101 O
1%
#2560000
0%
#2565000
b1010110 O
1%
#2570000
0%
#2575000
b1010111 O
1%
#2580000
0%
#2585000
b1011000 O
1%
#2590000
0%
#2595000
b1011001 O
1%
#2600000
0%
0'
#2605000
14
b1011010 O
0>
1%
#2610000
0%
#2615000
04
0?
b1011011 O
1%
#2620000
0%
#2625000
b1011100 O
1%
#2630000
0%
#2635000
b1011101 O
1%
#2640000
0%
#2645000
b1011110 O
1%
#2650000
0%
b110 Q
#2655000
b1011111 O
1%
#2660000
0%
#2665000
b1100000 O
1%
#2670000
0%
#2675000
b1100001 O
1%
#2680000
0%
#2685000
b1100010 O
1%
#2690000
0%
#2695000
b1100011 O
1%
#2700000
0%
#2705000
b1100100 O
1%
#2710000
0%
#2715000
b1100101 O
1%
#2720000
0%
#2725000
b1100110 O
1%
#2730000
0%
#2735000
b1100111 O
1%
#2740000
0%
#2745000
b1101000 O
1%
#2750000
0%
1'
#2755000
16
15
1>
b1101001 O
1%
#2760000
0%
#2765000
06
05
b1101010 O
b10000000 3
b10000000 B
b10 ;
1?
1%
#2770000
0%
#2775000
b1101011 O
1%
#2780000
0%
#2785000
b1101100 O
1%
#2790000
0%
#2795000
b1101101 O
1%
#2800000
0%
